Workbook

Sheet Cover
B3: Configuration Parameters
B5: Generated: | C5: April 07, 2026
B6: Solution: | C6: Intelligent Document Processing
B7: Customer: | C7: [Customer Name]
B8: Version: | C8: 1.0
B9: Status: | C9: Draft
C12: eoframework.org

Sheet All Parameters (Read Only)
A1: Total Parameters | B1: Categories | C1: Required | D1: Confidential/Secret
A2: 134 | B2: 8 | C2: 124 | D2: 6
A4: Parameter Name | B4: Category | C4: Production | D4: Test | E4: DR | F4: Description | G4: Required | H4: Data Type | I4: Validation Rules | J4: Security Level | K4: Owner Team | L4: Dependencies | M4: Notes | N4: Last Updated
A5: =IF('Project'!A3="","",'Project'!A3) | B5: Project | C5: =IF('Project'!B3="","",'Project'!B3) | D5: =IF('Project'!C3="","",'Project'!C3) | E5: =IF('Project'!D3="","",'Project'!D3) | F5: =IF('Project'!E3="","",'Project'!E3) | G5: =IF('Project'!F3="","",'Project'!F3) | H5: =IF('Project'!G3="","",'Project'!G3) | I5: =IF('Project'!H3="","",'Project'!H3) | J5: =IF('Project'!I3="","",'Project'!I3) | ... N5: =IF('Project'!M3="","",'Project'!M3)
A6: =IF('Project'!A4="","",'Project'!A4) | B6: Project | C6: =IF('Project'!B4="","",'Project'!B4) | D6: =IF('Project'!C4="","",'Project'!C4) | E6: =IF('Project'!D4="","",'Project'!D4) | F6: =IF('Project'!E4="","",'Project'!E4) | G6: =IF('Project'!F4="","",'Project'!F4) | H6: =IF('Project'!G4="","",'Project'!G4) | I6: =IF('Project'!H4="","",'Project'!H4) | J6: =IF('Project'!I4="","",'Project'!I4) | ... N6: =IF('Project'!M4="","",'Project'!M4)
A7: =IF('Project'!A5="","",'Project'!A5) | B7: Project | C7: =IF('Project'!B5="","",'Project'!B5) | D7: =IF('Project'!C5="","",'Project'!C5) | E7: =IF('Project'!D5="","",'Project'!D5) | F7: =IF('Project'!E5="","",'Project'!E5) | G7: =IF('Project'!F5="","",'Project'!F5) | H7: =IF('Project'!G5="","",'Project'!G5) | I7: =IF('Project'!H5="","",'Project'!H5) | J7: =IF('Project'!I5="","",'Project'!I5) | ... N7: =IF('Project'!M5="","",'Project'!M5)
A8: =IF('Project'!A6="","",'Project'!A6) | B8: Project | C8: =IF('Project'!B6="","",'Project'!B6) | D8: =IF('Project'!C6="","",'Project'!C6) | E8: =IF('Project'!D6="","",'Project'!D6) | F8: =IF('Project'!E6="","",'Project'!E6) | G8: =IF('Project'!F6="","",'Project'!F6) | H8: =IF('Project'!G6="","",'Project'!G6) | I8: =IF('Project'!H6="","",'Project'!H6) | J8: =IF('Project'!I6="","",'Project'!I6) | ... N8: =IF('Project'!M6="","",'Project'!M6)
A9: =IF('Project'!A7="","",'Project'!A7) | B9: Project | C9: =IF('Project'!B7="","",'Project'!B7) | D9: =IF('Project'!C7="","",'Project'!C7) | E9: =IF('Project'!D7="","",'Project'!D7) | F9: =IF('Project'!E7="","",'Project'!E7) | G9: =IF('Project'!F7="","",'Project'!F7) | H9: =IF('Project'!G7="","",'Project'!G7) | I9: =IF('Project'!H7="","",'Project'!H7) | J9: =IF('Project'!I7="","",'Project'!I7) | ... N9: =IF('Project'!M7="","",'Project'!M7)
A10: =IF('Project'!A8="","",'Project'!A8) | B10: Project | C10: =IF('Project'!B8="","",'Project'!B8) | D10: =IF('Project'!C8="","",'Project'!C8) | E10: =IF('Project'!D8="","",'Project'!D8) | F10: =IF('Project'!E8="","",'Project'!E8) | G10: =IF('Project'!F8="","",'Project'!F8) | H10: =IF('Project'!G8="","",'Project'!G8) | I10: =IF('Project'!H8="","",'Project'!H8) | J10: =IF('Project'!I8="","",'Project'!I8) | ... N10: =IF('Project'!M8="","",'Project'!M8)
A11: =IF('Project'!A9="","",'Project'!A9) | B11: Project | C11: =IF('Project'!B9="","",'Project'!B9) | D11: =IF('Project'!C9="","",'Project'!C9) | E11: =IF('Project'!D9="","",'Project'!D9) | F11: =IF('Project'!E9="","",'Project'!E9) | G11: =IF('Project'!F9="","",'Project'!F9) | H11: =IF('Project'!G9="","",'Project'!G9) | I11: =IF('Project'!H9="","",'Project'!H9) | J11: =IF('Project'!I9="","",'Project'!I9) | ... N11: =IF('Project'!M9="","",'Project'!M9)
A12: =IF('Project'!A10="","",'Project'!A10) | B12: Project | C12: =IF('Project'!B10="","",'Project'!B10) | D12: =IF('Project'!C10="","",'Project'!C10) | E12: =IF('Project'!D10="","",'Project'!D10) | F12: =IF('Project'!E10="","",'Project'!E10) | G12: =IF('Project'!F10="","",'Project'!F10) | H12: =IF('Project'!G10="","",'Project'!G10) | I12: =IF('Project'!H10="","",'Project'!H10) | J12: =IF('Project'!I10="","",'Project'!I10) | ... N12: =IF('Project'!M10="","",'Project'!M10)
A13: =IF('Project'!A11="","",'Project'!A11) | B13: Project | C13: =IF('Project'!B11="","",'Project'!B11) | D13: =IF('Project'!C11="","",'Project'!C11) | E13: =IF('Project'!D11="","",'Project'!D11) | F13: =IF('Project'!E11="","",'Project'!E11) | G13: =IF('Project'!F11="","",'Project'!F11) | H13: =IF('Project'!G11="","",'Project'!G11) | I13: =IF('Project'!H11="","",'Project'!H11) | J13: =IF('Project'!I11="","",'Project'!I11) | ... N13: =IF('Project'!M11="","",'Project'!M11)
A14: =IF('Project'!A12="","",'Project'!A12) | B14: Project | C14: =IF('Project'!B12="","",'Project'!B12) | D14: =IF('Project'!C12="","",'Project'!C12) | E14: =IF('Project'!D12="","",'Project'!D12) | F14: =IF('Project'!E12="","",'Project'!E12) | G14: =IF('Project'!F12="","",'Project'!F12) | H14: =IF('Project'!G12="","",'Project'!G12) | I14: =IF('Project'!H12="","",'Project'!H12) | J14: =IF('Project'!I12="","",'Project'!I12) | ... N14: =IF('Project'!M12="","",'Project'!M12)
A15: =IF('Security'!A3="","",'Security'!A3) | B15: Security | C15: =IF('Security'!B3="","",'Security'!B3) | D15: =IF('Security'!C3="","",'Security'!C3) | E15: =IF('Security'!D3="","",'Security'!D3) | F15: =IF('Security'!E3="","",'Security'!E3) | G15: =IF('Security'!F3="","",'Security'!F3) | H15: =IF('Security'!G3="","",'Security'!G3) | I15: =IF('Security'!H3="","",'Security'!H3) | J15: =IF('Security'!I3="","",'Security'!I3) | ... N15: =IF('Security'!M3="","",'Security'!M3)
A16: =IF('Security'!A4="","",'Security'!A4) | B16: Security | C16: =IF('Security'!B4="","",'Security'!B4) | D16: =IF('Security'!C4="","",'Security'!C4) | E16: =IF('Security'!D4="","",'Security'!D4) | F16: =IF('Security'!E4="","",'Security'!E4) | G16: =IF('Security'!F4="","",'Security'!F4) | H16: =IF('Security'!G4="","",'Security'!G4) | I16: =IF('Security'!H4="","",'Security'!H4) | J16: =IF('Security'!I4="","",'Security'!I4) | ... N16: =IF('Security'!M4="","",'Security'!M4)
A17: =IF('Security'!A5="","",'Security'!A5) | B17: Security | C17: =IF('Security'!B5="","",'Security'!B5) | D17: =IF('Security'!C5="","",'Security'!C5) | E17: =IF('Security'!D5="","",'Security'!D5) | F17: =IF('Security'!E5="","",'Security'!E5) | G17: =IF('Security'!F5="","",'Security'!F5) | H17: =IF('Security'!G5="","",'Security'!G5) | I17: =IF('Security'!H5="","",'Security'!H5) | J17: =IF('Security'!I5="","",'Security'!I5) | ... N17: =IF('Security'!M5="","",'Security'!M5)
A18: =IF('Security'!A6="","",'Security'!A6) | B18: Security | C18: =IF('Security'!B6="","",'Security'!B6) | D18: =IF('Security'!C6="","",'Security'!C6) | E18: =IF('Security'!D6="","",'Security'!D6) | F18: =IF('Security'!E6="","",'Security'!E6) | G18: =IF('Security'!F6="","",'Security'!F6) | H18: =IF('Security'!G6="","",'Security'!G6) | I18: =IF('Security'!H6="","",'Security'!H6) | J18: =IF('Security'!I6="","",'Security'!I6) | ... N18: =IF('Security'!M6="","",'Security'!M6)
A19: =IF('Security'!A7="","",'Security'!A7) | B19: Security | C19: =IF('Security'!B7="","",'Security'!B7) | D19: =IF('Security'!C7="","",'Security'!C7) | E19: =IF('Security'!D7="","",'Security'!D7) | F19: =IF('Security'!E7="","",'Security'!E7) | G19: =IF('Security'!F7="","",'Security'!F7) | H19: =IF('Security'!G7="","",'Security'!G7) | I19: =IF('Security'!H7="","",'Security'!H7) | J19: =IF('Security'!I7="","",'Security'!I7) | ... N19: =IF('Security'!M7="","",'Security'!M7)
A20: =IF('Security'!A8="","",'Security'!A8) | B20: Security | C20: =IF('Security'!B8="","",'Security'!B8) | D20: =IF('Security'!C8="","",'Security'!C8) | E20: =IF('Security'!D8="","",'Security'!D8) | F20: =IF('Security'!E8="","",'Security'!E8) | G20: =IF('Security'!F8="","",'Security'!F8) | H20: =IF('Security'!G8="","",'Security'!G8) | I20: =IF('Security'!H8="","",'Security'!H8) | J20: =IF('Security'!I8="","",'Security'!I8) | ... N20: =IF('Security'!M8="","",'Security'!M8)
A21: =IF('Security'!A9="","",'Security'!A9) | B21: Security | C21: =IF('Security'!B9="","",'Security'!B9) | D21: =IF('Security'!C9="","",'Security'!C9) | E21: =IF('Security'!D9="","",'Security'!D9) | F21: =IF('Security'!E9="","",'Security'!E9) | G21: =IF('Security'!F9="","",'Security'!F9) | H21: =IF('Security'!G9="","",'Security'!G9) | I21: =IF('Security'!H9="","",'Security'!H9) | J21: =IF('Security'!I9="","",'Security'!I9) | ... N21: =IF('Security'!M9="","",'Security'!M9)
A22: =IF('Security'!A10="","",'Security'!A10) | B22: Security | C22: =IF('Security'!B10="","",'Security'!B10) | D22: =IF('Security'!C10="","",'Security'!C10) | E22: =IF('Security'!D10="","",'Security'!D10) | F22: =IF('Security'!E10="","",'Security'!E10) | G22: =IF('Security'!F10="","",'Security'!F10) | H22: =IF('Security'!G10="","",'Security'!G10) | I22: =IF('Security'!H10="","",'Security'!H10) | J22: =IF('Security'!I10="","",'Security'!I10) | ... N22: =IF('Security'!M10="","",'Security'!M10)
A23: =IF('Security'!A11="","",'Security'!A11) | B23: Security | C23: =IF('Security'!B11="","",'Security'!B11) | D23: =IF('Security'!C11="","",'Security'!C11) | E23: =IF('Security'!D11="","",'Security'!D11) | F23: =IF('Security'!E11="","",'Security'!E11) | G23: =IF('Security'!F11="","",'Security'!F11) | H23: =IF('Security'!G11="","",'Security'!G11) | I23: =IF('Security'!H11="","",'Security'!H11) | J23: =IF('Security'!I11="","",'Security'!I11) | ... N23: =IF('Security'!M11="","",'Security'!M11)
A24: =IF('Security'!A12="","",'Security'!A12) | B24: Security | C24: =IF('Security'!B12="","",'Security'!B12) | D24: =IF('Security'!C12="","",'Security'!C12) | E24: =IF('Security'!D12="","",'Security'!D12) | F24: =IF('Security'!E12="","",'Security'!E12) | G24: =IF('Security'!F12="","",'Security'!F12) | H24: =IF('Security'!G12="","",'Security'!G12) | I24: =IF('Security'!H12="","",'Security'!H12) | J24: =IF('Security'!I12="","",'Security'!I12) | ... N24: =IF('Security'!M12="","",'Security'!M12)
A25: =IF('Security'!A13="","",'Security'!A13) | B25: Security | C25: =IF('Security'!B13="","",'Security'!B13) | D25: =IF('Security'!C13="","",'Security'!C13) | E25: =IF('Security'!D13="","",'Security'!D13) | F25: =IF('Security'!E13="","",'Security'!E13) | G25: =IF('Security'!F13="","",'Security'!F13) | H25: =IF('Security'!G13="","",'Security'!G13) | I25: =IF('Security'!H13="","",'Security'!H13) | J25: =IF('Security'!I13="","",'Security'!I13) | ... N25: =IF('Security'!M13="","",'Security'!M13)
A26: =IF('Security'!A14="","",'Security'!A14) | B26: Security | C26: =IF('Security'!B14="","",'Security'!B14) | D26: =IF('Security'!C14="","",'Security'!C14) | E26: =IF('Security'!D14="","",'Security'!D14) | F26: =IF('Security'!E14="","",'Security'!E14) | G26: =IF('Security'!F14="","",'Security'!F14) | H26: =IF('Security'!G14="","",'Security'!G14) | I26: =IF('Security'!H14="","",'Security'!H14) | J26: =IF('Security'!I14="","",'Security'!I14) | ... N26: =IF('Security'!M14="","",'Security'!M14)
... A29: =IF('Security'!A17="","",'Security'!A17) | B29: Security | C29: =IF('Security'!B17="","",'Security'!B17) | D29: =IF('Security'!C17="","",'Security'!C17) | E29: =IF('Security'!D17="","",'Security'!D17) | F29: =IF('Security'!E17="","",'Security'!E17) | G29: =IF('Security'!F17="","",'Security'!F17) | H29: =IF('Security'!G17="","",'Security'!G17) | I29: =IF('Security'!H17="","",'Security'!H17) | J29: =IF('Security'!I17="","",'Security'!I17) | ... N29: =IF('Security'!M17="","",'Security'!M17)
A30: =IF('Storage'!A3="","",'Storage'!A3) | B30: Storage | C30: =IF('Storage'!B3="","",'Storage'!B3) | D30: =IF('Storage'!C3="","",'Storage'!C3) | E30: =IF('Storage'!D3="","",'Storage'!D3) | F30: =IF('Storage'!E3="","",'Storage'!E3) | G30: =IF('Storage'!F3="","",'Storage'!F3) | H30: =IF('Storage'!G3="","",'Storage'!G3) | I30: =IF('Storage'!H3="","",'Storage'!H3) | J30: =IF('Storage'!I3="","",'Storage'!I3) | ... N30: =IF('Storage'!M3="","",'Storage'!M3)
A31: =IF('Storage'!A4="","",'Storage'!A4) | B31: Storage | C31: =IF('Storage'!B4="","",'Storage'!B4) | D31: =IF('Storage'!C4="","",'Storage'!C4) | E31: =IF('Storage'!D4="","",'Storage'!D4) | F31: =IF('Storage'!E4="","",'Storage'!E4) | G31: =IF('Storage'!F4="","",'Storage'!F4) | H31: =IF('Storage'!G4="","",'Storage'!G4) | I31: =IF('Storage'!H4="","",'Storage'!H4) | J31: =IF('Storage'!I4="","",'Storage'!I4) | ... N31: =IF('Storage'!M4="","",'Storage'!M4)
A32: =IF('Storage'!A5="","",'Storage'!A5) | B32: Storage | C32: =IF('Storage'!B5="","",'Storage'!B5) | D32: =IF('Storage'!C5="","",'Storage'!C5) | E32: =IF('Storage'!D5="","",'Storage'!D5) | F32: =IF('Storage'!E5="","",'Storage'!E5) | G32: =IF('Storage'!F5="","",'Storage'!F5) | H32: =IF('Storage'!G5="","",'Storage'!G5) | I32: =IF('Storage'!H5="","",'Storage'!H5) | J32: =IF('Storage'!I5="","",'Storage'!I5) | ... N32: =IF('Storage'!M5="","",'Storage'!M5)
A33: =IF('Storage'!A6="","",'Storage'!A6) | B33: Storage | C33: =IF('Storage'!B6="","",'Storage'!B6) | D33: =IF('Storage'!C6="","",'Storage'!C6) | E33: =IF('Storage'!D6="","",'Storage'!D6) | F33: =IF('Storage'!E6="","",'Storage'!E6) | G33: =IF('Storage'!F6="","",'Storage'!F6) | H33: =IF('Storage'!G6="","",'Storage'!G6) | I33: =IF('Storage'!H6="","",'Storage'!H6) | J33: =IF('Storage'!I6="","",'Storage'!I6) | ... N33: =IF('Storage'!M6="","",'Storage'!M6)
A34: =IF('Storage'!A7="","",'Storage'!A7) | B34: Storage | C34: =IF('Storage'!B7="","",'Storage'!B7) | D34: =IF('Storage'!C7="","",'Storage'!C7) | E34: =IF('Storage'!D7="","",'Storage'!D7) | F34: =IF('Storage'!E7="","",'Storage'!E7) | G34: =IF('Storage'!F7="","",'Storage'!F7) | H34: =IF('Storage'!G7="","",'Storage'!G7) | I34: =IF('Storage'!H7="","",'Storage'!H7) | J34: =IF('Storage'!I7="","",'Storage'!I7) | ... N34: =IF('Storage'!M7="","",'Storage'!M7)
A35: =IF('Storage'!A8="","",'Storage'!A8) | B35: Storage | C35: =IF('Storage'!B8="","",'Storage'!B8) | D35: =IF('Storage'!C8="","",'Storage'!C8) | E35: =IF('Storage'!D8="","",'Storage'!D8) | F35: =IF('Storage'!E8="","",'Storage'!E8) | G35: =IF('Storage'!F8="","",'Storage'!F8) | H35: =IF('Storage'!G8="","",'Storage'!G8) | I35: =IF('Storage'!H8="","",'Storage'!H8) | J35: =IF('Storage'!I8="","",'Storage'!I8) | ... N35: =IF('Storage'!M8="","",'Storage'!M8)
A36: =IF('Storage'!A9="","",'Storage'!A9) | B36: Storage | C36: =IF('Storage'!B9="","",'Storage'!B9) | D36: =IF('Storage'!C9="","",'Storage'!C9) | E36: =IF('Storage'!D9="","",'Storage'!D9) | F36: =IF('Storage'!E9="","",'Storage'!E9) | G36: =IF('Storage'!F9="","",'Storage'!F9) | H36: =IF('Storage'!G9="","",'Storage'!G9) | I36: =IF('Storage'!H9="","",'Storage'!H9) | J36: =IF('Storage'!I9="","",'Storage'!I9) | ... N36: =IF('Storage'!M9="","",'Storage'!M9)
A37: =IF('Storage'!A10="","",'Storage'!A10) | B37: Storage | C37: =IF('Storage'!B10="","",'Storage'!B10) | D37: =IF('Storage'!C10="","",'Storage'!C10) | E37: =IF('Storage'!D10="","",'Storage'!D10) | F37: =IF('Storage'!E10="","",'Storage'!E10) | G37: =IF('Storage'!F10="","",'Storage'!F10) | H37: =IF('Storage'!G10="","",'Storage'!G10) | I37: =IF('Storage'!H10="","",'Storage'!H10) | J37: =IF('Storage'!I10="","",'Storage'!I10) | ... N37: =IF('Storage'!M10="","",'Storage'!M10)
A38: =IF('Storage'!A11="","",'Storage'!A11) | B38: Storage | C38: =IF('Storage'!B11="","",'Storage'!B11) | D38: =IF('Storage'!C11="","",'Storage'!C11) | E38: =IF('Storage'!D11="","",'Storage'!D11) | F38: =IF('Storage'!E11="","",'Storage'!E11) | G38: =IF('Storage'!F11="","",'Storage'!F11) | H38: =IF('Storage'!G11="","",'Storage'!G11) | I38: =IF('Storage'!H11="","",'Storage'!H11) | J38: =IF('Storage'!I11="","",'Storage'!I11) | ... N38: =IF('Storage'!M11="","",'Storage'!M11)
A39: =IF('Storage'!A12="","",'Storage'!A12) | B39: Storage | C39: =IF('Storage'!B12="","",'Storage'!B12) | D39: =IF('Storage'!C12="","",'Storage'!C12) | E39: =IF('Storage'!D12="","",'Storage'!D12) | F39: =IF('Storage'!E12="","",'Storage'!E12) | G39: =IF('Storage'!F12="","",'Storage'!F12) | H39: =IF('Storage'!G12="","",'Storage'!G12) | I39: =IF('Storage'!H12="","",'Storage'!H12) | J39: =IF('Storage'!I12="","",'Storage'!I12) | ... N39: =IF('Storage'!M12="","",'Storage'!M12)
A40: =IF('Database'!A3="","",'Database'!A3) | B40: Database | C40: =IF('Database'!B3="","",'Database'!B3) | D40: =IF('Database'!C3="","",'Database'!C3) | E40: =IF('Database'!D3="","",'Database'!D3) | F40: =IF('Database'!E3="","",'Database'!E3) | G40: =IF('Database'!F3="","",'Database'!F3) | H40: =IF('Database'!G3="","",'Database'!G3) | I40: =IF('Database'!H3="","",'Database'!H3) | J40: =IF('Database'!I3="","",'Database'!I3) | ... N40: =IF('Database'!M3="","",'Database'!M3)
A41: =IF('Database'!A4="","",'Database'!A4) | B41: Database | C41: =IF('Database'!B4="","",'Database'!B4) | D41: =IF('Database'!C4="","",'Database'!C4) | E41: =IF('Database'!D4="","",'Database'!D4) | F41: =IF('Database'!E4="","",'Database'!E4) | G41: =IF('Database'!F4="","",'Database'!F4) | H41: =IF('Database'!G4="","",'Database'!G4) | I41: =IF('Database'!H4="","",'Database'!H4) | J41: =IF('Database'!I4="","",'Database'!I4) | ... N41: =IF('Database'!M4="","",'Database'!M4)
A42: =IF('Database'!A5="","",'Database'!A5) | B42: Database | C42: =IF('Database'!B5="","",'Database'!B5) | D42: =IF('Database'!C5="","",'Database'!C5) | E42: =IF('Database'!D5="","",'Database'!D5) | F42: =IF('Database'!E5="","",'Database'!E5) | G42: =IF('Database'!F5="","",'Database'!F5) | H42: =IF('Database'!G5="","",'Database'!G5) | I42: =IF('Database'!H5="","",'Database'!H5) | J42: =IF('Database'!I5="","",'Database'!I5) | ... N42: =IF('Database'!M5="","",'Database'!M5)
A43: =IF('Database'!A6="","",'Database'!A6) | B43: Database | C43: =IF('Database'!B6="","",'Database'!B6) | D43: =IF('Database'!C6="","",'Database'!C6) | E43: =IF('Database'!D6="","",'Database'!D6) | F43: =IF('Database'!E6="","",'Database'!E6) | G43: =IF('Database'!F6="","",'Database'!F6) | H43: =IF('Database'!G6="","",'Database'!G6) | I43: =IF('Database'!H6="","",'Database'!H6) | J43: =IF('Database'!I6="","",'Database'!I6) | ... N43: =IF('Database'!M6="","",'Database'!M6)
A44: =IF('Database'!A7="","",'Database'!A7) | B44: Database | C44: =IF('Database'!B7="","",'Database'!B7) | D44: =IF('Database'!C7="","",'Database'!C7) | E44: =IF('Database'!D7="","",'Database'!D7) | F44: =IF('Database'!E7="","",'Database'!E7) | G44: =IF('Database'!F7="","",'Database'!F7) | H44: =IF('Database'!G7="","",'Database'!G7) | I44: =IF('Database'!H7="","",'Database'!H7) | J44: =IF('Database'!I7="","",'Database'!I7) | ... N44: =IF('Database'!M7="","",'Database'!M7)
A45: =IF('Database'!A8="","",'Database'!A8) | B45: Database | C45: =IF('Database'!B8="","",'Database'!B8) | D45: =IF('Database'!C8="","",'Database'!C8) | E45: =IF('Database'!D8="","",'Database'!D8) | F45: =IF('Database'!E8="","",'Database'!E8) | G45: =IF('Database'!F8="","",'Database'!F8) | H45: =IF('Database'!G8="","",'Database'!G8) | I45: =IF('Database'!H8="","",'Database'!H8) | J45: =IF('Database'!I8="","",'Database'!I8) | ... N45: =IF('Database'!M8="","",'Database'!M8)
A46: =IF('Database'!A9="","",'Database'!A9) | B46: Database | C46: =IF('Database'!B9="","",'Database'!B9) | D46: =IF('Database'!C9="","",'Database'!C9) | E46: =IF('Database'!D9="","",'Database'!D9) | F46: =IF('Database'!E9="","",'Database'!E9) | G46: =IF('Database'!F9="","",'Database'!F9) | H46: =IF('Database'!G9="","",'Database'!G9) | I46: =IF('Database'!H9="","",'Database'!H9) | J46: =IF('Database'!I9="","",'Database'!I9) | ... N46: =IF('Database'!M9="","",'Database'!M9)
A47: =IF('Database'!A10="","",'Database'!A10) | B47: Database | C47: =IF('Database'!B10="","",'Database'!B10) | D47: =IF('Database'!C10="","",'Database'!C10) | E47: =IF('Database'!D10="","",'Database'!D10) | F47: =IF('Database'!E10="","",'Database'!E10) | G47: =IF('Database'!F10="","",'Database'!F10) | H47: =IF('Database'!G10="","",'Database'!G10) | I47: =IF('Database'!H10="","",'Database'!H10) | J47: =IF('Database'!I10="","",'Database'!I10) | ... N47: =IF('Database'!M10="","",'Database'!M10)
A48: =IF('Database'!A11="","",'Database'!A11) | B48: Database | C48: =IF('Database'!B11="","",'Database'!B11) | D48: =IF('Database'!C11="","",'Database'!C11) | E48: =IF('Database'!D11="","",'Database'!D11) | F48: =IF('Database'!E11="","",'Database'!E11) | G48: =IF('Database'!F11="","",'Database'!F11) | H48: =IF('Database'!G11="","",'Database'!G11) | I48: =IF('Database'!H11="","",'Database'!H11) | J48: =IF('Database'!I11="","",'Database'!I11) | ... N48: =IF('Database'!M11="","",'Database'!M11)
A49: =IF('Database'!A12="","",'Database'!A12) | B49: Database | C49: =IF('Database'!B12="","",'Database'!B12) | D49: =IF('Database'!C12="","",'Database'!C12) | E49: =IF('Database'!D12="","",'Database'!D12) | F49: =IF('Database'!E12="","",'Database'!E12) | G49: =IF('Database'!F12="","",'Database'!F12) | H49: =IF('Database'!G12="","",'Database'!G12) | I49: =IF('Database'!H12="","",'Database'!H12) | J49: =IF('Database'!I12="","",'Database'!I12) | ... N49: =IF('Database'!M12="","",'Database'!M12)
A50: =IF('Database'!A13="","",'Database'!A13) | B50: Database | C50: =IF('Database'!B13="","",'Database'!B13) | D50: =IF('Database'!C13="","",'Database'!C13) | E50: =IF('Database'!D13="","",'Database'!D13) | F50: =IF('Database'!E13="","",'Database'!E13) | G50: =IF('Database'!F13="","",'Database'!F13) | H50: =IF('Database'!G13="","",'Database'!G13) | I50: =IF('Database'!H13="","",'Database'!H13) | J50: =IF('Database'!I13="","",'Database'!I13) | ... N50: =IF('Database'!M13="","",'Database'!M13)
A51: =IF('Database'!A14="","",'Database'!A14) | B51: Database | C51: =IF('Database'!B14="","",'Database'!B14) | D51: =IF('Database'!C14="","",'Database'!C14) | E51: =IF('Database'!D14="","",'Database'!D14) | F51: =IF('Database'!E14="","",'Database'!E14) | G51: =IF('Database'!F14="","",'Database'!F14) | H51: =IF('Database'!G14="","",'Database'!G14) | I51: =IF('Database'!H14="","",'Database'!H14) | J51: =IF('Database'!I14="","",'Database'!I14) | ... N51: =IF('Database'!M14="","",'Database'!M14)
... A54: =IF('Database'!A17="","",'Database'!A17) | B54: Database | C54: =IF('Database'!B17="","",'Database'!B17) | D54: =IF('Database'!C17="","",'Database'!C17) | E54: =IF('Database'!D17="","",'Database'!D17) | F54: =IF('Database'!E17="","",'Database'!E17) | G54: =IF('Database'!F17="","",'Database'!F17) | H54: =IF('Database'!G17="","",'Database'!G17) | I54: =IF('Database'!H17="","",'Database'!H17) | J54: =IF('Database'!I17="","",'Database'!I17) | ... N54: =IF('Database'!M17="","",'Database'!M17)
A55: =IF('Application'!A3="","",'Application'!A3) | B55: Application | C55: =IF('Application'!B3="","",'Application'!B3) | D55: =IF('Application'!C3="","",'Application'!C3) | E55: =IF('Application'!D3="","",'Application'!D3) | F55: =IF('Application'!E3="","",'Application'!E3) | G55: =IF('Application'!F3="","",'Application'!F3) | H55: =IF('Application'!G3="","",'Application'!G3) | I55: =IF('Application'!H3="","",'Application'!H3) | J55: =IF('Application'!I3="","",'Application'!I3) | ... N55: =IF('Application'!M3="","",'Application'!M3)
A56: =IF('Application'!A4="","",'Application'!A4) | B56: Application | C56: =IF('Application'!B4="","",'Application'!B4) | D56: =IF('Application'!C4="","",'Application'!C4) | E56: =IF('Application'!D4="","",'Application'!D4) | F56: =IF('Application'!E4="","",'Application'!E4) | G56: =IF('Application'!F4="","",'Application'!F4) | H56: =IF('Application'!G4="","",'Application'!G4) | I56: =IF('Application'!H4="","",'Application'!H4) | J56: =IF('Application'!I4="","",'Application'!I4) | ... N56: =IF('Application'!M4="","",'Application'!M4)
A57: =IF('Application'!A5="","",'Application'!A5) | B57: Application | C57: =IF('Application'!B5="","",'Application'!B5) | D57: =IF('Application'!C5="","",'Application'!C5) | E57: =IF('Application'!D5="","",'Application'!D5) | F57: =IF('Application'!E5="","",'Application'!E5) | G57: =IF('Application'!F5="","",'Application'!F5) | H57: =IF('Application'!G5="","",'Application'!G5) | I57: =IF('Application'!H5="","",'Application'!H5) | J57: =IF('Application'!I5="","",'Application'!I5) | ... N57: =IF('Application'!M5="","",'Application'!M5)
A58: =IF('Application'!A6="","",'Application'!A6) | B58: Application | C58: =IF('Application'!B6="","",'Application'!B6) | D58: =IF('Application'!C6="","",'Application'!C6) | E58: =IF('Application'!D6="","",'Application'!D6) | F58: =IF('Application'!E6="","",'Application'!E6) | G58: =IF('Application'!F6="","",'Application'!F6) | H58: =IF('Application'!G6="","",'Application'!G6) | I58: =IF('Application'!H6="","",'Application'!H6) | J58: =IF('Application'!I6="","",'Application'!I6) | ... N58: =IF('Application'!M6="","",'Application'!M6)
A59: =IF('Application'!A7="","",'Application'!A7) | B59: Application | C59: =IF('Application'!B7="","",'Application'!B7) | D59: =IF('Application'!C7="","",'Application'!C7) | E59: =IF('Application'!D7="","",'Application'!D7) | F59: =IF('Application'!E7="","",'Application'!E7) | G59: =IF('Application'!F7="","",'Application'!F7) | H59: =IF('Application'!G7="","",'Application'!G7) | I59: =IF('Application'!H7="","",'Application'!H7) | J59: =IF('Application'!I7="","",'Application'!I7) | ... N59: =IF('Application'!M7="","",'Application'!M7)
A60: =IF('Application'!A8="","",'Application'!A8) | B60: Application | C60: =IF('Application'!B8="","",'Application'!B8) | D60: =IF('Application'!C8="","",'Application'!C8) | E60: =IF('Application'!D8="","",'Application'!D8) | F60: =IF('Application'!E8="","",'Application'!E8) | G60: =IF('Application'!F8="","",'Application'!F8) | H60: =IF('Application'!G8="","",'Application'!G8) | I60: =IF('Application'!H8="","",'Application'!H8) | J60: =IF('Application'!I8="","",'Application'!I8) | ... N60: =IF('Application'!M8="","",'Application'!M8)
A61: =IF('Application'!A9="","",'Application'!A9) | B61: Application | C61: =IF('Application'!B9="","",'Application'!B9) | D61: =IF('Application'!C9="","",'Application'!C9) | E61: =IF('Application'!D9="","",'Application'!D9) | F61: =IF('Application'!E9="","",'Application'!E9) | G61: =IF('Application'!F9="","",'Application'!F9) | H61: =IF('Application'!G9="","",'Application'!G9) | I61: =IF('Application'!H9="","",'Application'!H9) | J61: =IF('Application'!I9="","",'Application'!I9) | ... N61: =IF('Application'!M9="","",'Application'!M9)
A62: =IF('Application'!A10="","",'Application'!A10) | B62: Application | C62: =IF('Application'!B10="","",'Application'!B10) | D62: =IF('Application'!C10="","",'Application'!C10) | E62: =IF('Application'!D10="","",'Application'!D10) | F62: =IF('Application'!E10="","",'Application'!E10) | G62: =IF('Application'!F10="","",'Application'!F10) | H62: =IF('Application'!G10="","",'Application'!G10) | I62: =IF('Application'!H10="","",'Application'!H10) | J62: =IF('Application'!I10="","",'Application'!I10) | ... N62: =IF('Application'!M10="","",'Application'!M10)
A63: =IF('Application'!A11="","",'Application'!A11) | B63: Application | C63: =IF('Application'!B11="","",'Application'!B11) | D63: =IF('Application'!C11="","",'Application'!C11) | E63: =IF('Application'!D11="","",'Application'!D11) | F63: =IF('Application'!E11="","",'Application'!E11) | G63: =IF('Application'!F11="","",'Application'!F11) | H63: =IF('Application'!G11="","",'Application'!G11) | I63: =IF('Application'!H11="","",'Application'!H11) | J63: =IF('Application'!I11="","",'Application'!I11) | ... N63: =IF('Application'!M11="","",'Application'!M11)
A64: =IF('Application'!A12="","",'Application'!A12) | B64: Application | C64: =IF('Application'!B12="","",'Application'!B12) | D64: =IF('Application'!C12="","",'Application'!C12) | E64: =IF('Application'!D12="","",'Application'!D12) | F64: =IF('Application'!E12="","",'Application'!E12) | G64: =IF('Application'!F12="","",'Application'!F12) | H64: =IF('Application'!G12="","",'Application'!G12) | I64: =IF('Application'!H12="","",'Application'!H12) | J64: =IF('Application'!I12="","",'Application'!I12) | ... N64: =IF('Application'!M12="","",'Application'!M12)
A65: =IF('Application'!A13="","",'Application'!A13) | B65: Application | C65: =IF('Application'!B13="","",'Application'!B13) | D65: =IF('Application'!C13="","",'Application'!C13) | E65: =IF('Application'!D13="","",'Application'!D13) | F65: =IF('Application'!E13="","",'Application'!E13) | G65: =IF('Application'!F13="","",'Application'!F13) | H65: =IF('Application'!G13="","",'Application'!G13) | I65: =IF('Application'!H13="","",'Application'!H13) | J65: =IF('Application'!I13="","",'Application'!I13) | ... N65: =IF('Application'!M13="","",'Application'!M13)
A66: =IF('Application'!A14="","",'Application'!A14) | B66: Application | C66: =IF('Application'!B14="","",'Application'!B14) | D66: =IF('Application'!C14="","",'Application'!C14) | E66: =IF('Application'!D14="","",'Application'!D14) | F66: =IF('Application'!E14="","",'Application'!E14) | G66: =IF('Application'!F14="","",'Application'!F14) | H66: =IF('Application'!G14="","",'Application'!G14) | I66: =IF('Application'!H14="","",'Application'!H14) | J66: =IF('Application'!I14="","",'Application'!I14) | ... N66: =IF('Application'!M14="","",'Application'!M14)
... A92: =IF('Application'!A40="","",'Application'!A40) | B92: Application | C92: =IF('Application'!B40="","",'Application'!B40) | D92: =IF('Application'!C40="","",'Application'!C40) | E92: =IF('Application'!D40="","",'Application'!D40) | F92: =IF('Application'!E40="","",'Application'!E40) | G92: =IF('Application'!F40="","",'Application'!F40) | H92: =IF('Application'!G40="","",'Application'!G40) | I92: =IF('Application'!H40="","",'Application'!H40) | J92: =IF('Application'!I40="","",'Application'!I40) | ... N92: =IF('Application'!M40="","",'Application'!M40)
A93: =IF('Monitoring'!A3="","",'Monitoring'!A3) | B93: Monitoring | C93: =IF('Monitoring'!B3="","",'Monitoring'!B3) | D93: =IF('Monitoring'!C3="","",'Monitoring'!C3) | E93: =IF('Monitoring'!D3="","",'Monitoring'!D3) | F93: =IF('Monitoring'!E3="","",'Monitoring'!E3) | G93: =IF('Monitoring'!F3="","",'Monitoring'!F3) | H93: =IF('Monitoring'!G3="","",'Monitoring'!G3) | I93: =IF('Monitoring'!H3="","",'Monitoring'!H3) | J93: =IF('Monitoring'!I3="","",'Monitoring'!I3) | ... N93: =IF('Monitoring'!M3="","",'Monitoring'!M3)
A94: =IF('Monitoring'!A4="","",'Monitoring'!A4) | B94: Monitoring | C94: =IF('Monitoring'!B4="","",'Monitoring'!B4) | D94: =IF('Monitoring'!C4="","",'Monitoring'!C4) | E94: =IF('Monitoring'!D4="","",'Monitoring'!D4) | F94: =IF('Monitoring'!E4="","",'Monitoring'!E4) | G94: =IF('Monitoring'!F4="","",'Monitoring'!F4) | H94: =IF('Monitoring'!G4="","",'Monitoring'!G4) | I94: =IF('Monitoring'!H4="","",'Monitoring'!H4) | J94: =IF('Monitoring'!I4="","",'Monitoring'!I4) | ... N94: =IF('Monitoring'!M4="","",'Monitoring'!M4)
A95: =IF('Monitoring'!A5="","",'Monitoring'!A5) | B95: Monitoring | C95: =IF('Monitoring'!B5="","",'Monitoring'!B5) | D95: =IF('Monitoring'!C5="","",'Monitoring'!C5) | E95: =IF('Monitoring'!D5="","",'Monitoring'!D5) | F95: =IF('Monitoring'!E5="","",'Monitoring'!E5) | G95: =IF('Monitoring'!F5="","",'Monitoring'!F5) | H95: =IF('Monitoring'!G5="","",'Monitoring'!G5) | I95: =IF('Monitoring'!H5="","",'Monitoring'!H5) | J95: =IF('Monitoring'!I5="","",'Monitoring'!I5) | ... N95: =IF('Monitoring'!M5="","",'Monitoring'!M5)
A96: =IF('Monitoring'!A6="","",'Monitoring'!A6) | B96: Monitoring | C96: =IF('Monitoring'!B6="","",'Monitoring'!B6) | D96: =IF('Monitoring'!C6="","",'Monitoring'!C6) | E96: =IF('Monitoring'!D6="","",'Monitoring'!D6) | F96: =IF('Monitoring'!E6="","",'Monitoring'!E6) | G96: =IF('Monitoring'!F6="","",'Monitoring'!F6) | H96: =IF('Monitoring'!G6="","",'Monitoring'!G6) | I96: =IF('Monitoring'!H6="","",'Monitoring'!H6) | J96: =IF('Monitoring'!I6="","",'Monitoring'!I6) | ... N96: =IF('Monitoring'!M6="","",'Monitoring'!M6)
A97: =IF('Monitoring'!A7="","",'Monitoring'!A7) | B97: Monitoring | C97: =IF('Monitoring'!B7="","",'Monitoring'!B7) | D97: =IF('Monitoring'!C7="","",'Monitoring'!C7) | E97: =IF('Monitoring'!D7="","",'Monitoring'!D7) | F97: =IF('Monitoring'!E7="","",'Monitoring'!E7) | G97: =IF('Monitoring'!F7="","",'Monitoring'!F7) | H97: =IF('Monitoring'!G7="","",'Monitoring'!G7) | I97: =IF('Monitoring'!H7="","",'Monitoring'!H7) | J97: =IF('Monitoring'!I7="","",'Monitoring'!I7) | ... N97: =IF('Monitoring'!M7="","",'Monitoring'!M7)
A98: =IF('Monitoring'!A8="","",'Monitoring'!A8) | B98: Monitoring | C98: =IF('Monitoring'!B8="","",'Monitoring'!B8) | D98: =IF('Monitoring'!C8="","",'Monitoring'!C8) | E98: =IF('Monitoring'!D8="","",'Monitoring'!D8) | F98: =IF('Monitoring'!E8="","",'Monitoring'!E8) | G98: =IF('Monitoring'!F8="","",'Monitoring'!F8) | H98: =IF('Monitoring'!G8="","",'Monitoring'!G8) | I98: =IF('Monitoring'!H8="","",'Monitoring'!H8) | J98: =IF('Monitoring'!I8="","",'Monitoring'!I8) | ... N98: =IF('Monitoring'!M8="","",'Monitoring'!M8)
A99: =IF('Monitoring'!A9="","",'Monitoring'!A9) | B99: Monitoring | C99: =IF('Monitoring'!B9="","",'Monitoring'!B9) | D99: =IF('Monitoring'!C9="","",'Monitoring'!C9) | E99: =IF('Monitoring'!D9="","",'Monitoring'!D9) | F99: =IF('Monitoring'!E9="","",'Monitoring'!E9) | G99: =IF('Monitoring'!F9="","",'Monitoring'!F9) | H99: =IF('Monitoring'!G9="","",'Monitoring'!G9) | I99: =IF('Monitoring'!H9="","",'Monitoring'!H9) | J99: =IF('Monitoring'!I9="","",'Monitoring'!I9) | ... N99: =IF('Monitoring'!M9="","",'Monitoring'!M9)
A100: =IF('Monitoring'!A10="","",'Monitoring'!A10) | B100: Monitoring | C100: =IF('Monitoring'!B10="","",'Monitoring'!B10) | D100: =IF('Monitoring'!C10="","",'Monitoring'!C10) | E100: =IF('Monitoring'!D10="","",'Monitoring'!D10) | F100: =IF('Monitoring'!E10="","",'Monitoring'!E10) | G100: =IF('Monitoring'!F10="","",'Monitoring'!F10) | H100: =IF('Monitoring'!G10="","",'Monitoring'!G10) | I100: =IF('Monitoring'!H10="","",'Monitoring'!H10) | J100: =IF('Monitoring'!I10="","",'Monitoring'!I10) | ... N100: =IF('Monitoring'!M10="","",'Monitoring'!M10)
A101: =IF('Monitoring'!A11="","",'Monitoring'!A11) | B101: Monitoring | C101: =IF('Monitoring'!B11="","",'Monitoring'!B11) | D101: =IF('Monitoring'!C11="","",'Monitoring'!C11) | E101: =IF('Monitoring'!D11="","",'Monitoring'!D11) | F101: =IF('Monitoring'!E11="","",'Monitoring'!E11) | G101: =IF('Monitoring'!F11="","",'Monitoring'!F11) | H101: =IF('Monitoring'!G11="","",'Monitoring'!G11) | I101: =IF('Monitoring'!H11="","",'Monitoring'!H11) | J101: =IF('Monitoring'!I11="","",'Monitoring'!I11) | ... N101: =IF('Monitoring'!M11="","",'Monitoring'!M11)
A102: =IF('Monitoring'!A12="","",'Monitoring'!A12) | B102: Monitoring | C102: =IF('Monitoring'!B12="","",'Monitoring'!B12) | D102: =IF('Monitoring'!C12="","",'Monitoring'!C12) | E102: =IF('Monitoring'!D12="","",'Monitoring'!D12) | F102: =IF('Monitoring'!E12="","",'Monitoring'!E12) | G102: =IF('Monitoring'!F12="","",'Monitoring'!F12) | H102: =IF('Monitoring'!G12="","",'Monitoring'!G12) | I102: =IF('Monitoring'!H12="","",'Monitoring'!H12) | J102: =IF('Monitoring'!I12="","",'Monitoring'!I12) | ... N102: =IF('Monitoring'!M12="","",'Monitoring'!M12)
A103: =IF('Monitoring'!A13="","",'Monitoring'!A13) | B103: Monitoring | C103: =IF('Monitoring'!B13="","",'Monitoring'!B13) | D103: =IF('Monitoring'!C13="","",'Monitoring'!C13) | E103: =IF('Monitoring'!D13="","",'Monitoring'!D13) | F103: =IF('Monitoring'!E13="","",'Monitoring'!E13) | G103: =IF('Monitoring'!F13="","",'Monitoring'!F13) | H103: =IF('Monitoring'!G13="","",'Monitoring'!G13) | I103: =IF('Monitoring'!H13="","",'Monitoring'!H13) | J103: =IF('Monitoring'!I13="","",'Monitoring'!I13) | ... N103: =IF('Monitoring'!M13="","",'Monitoring'!M13)
A104: =IF('Monitoring'!A14="","",'Monitoring'!A14) | B104: Monitoring | C104: =IF('Monitoring'!B14="","",'Monitoring'!B14) | D104: =IF('Monitoring'!C14="","",'Monitoring'!C14) | E104: =IF('Monitoring'!D14="","",'Monitoring'!D14) | F104: =IF('Monitoring'!E14="","",'Monitoring'!E14) | G104: =IF('Monitoring'!F14="","",'Monitoring'!F14) | H104: =IF('Monitoring'!G14="","",'Monitoring'!G14) | I104: =IF('Monitoring'!H14="","",'Monitoring'!H14) | J104: =IF('Monitoring'!I14="","",'Monitoring'!I14) | ... N104: =IF('Monitoring'!M14="","",'Monitoring'!M14)
A105: =IF('Monitoring'!A15="","",'Monitoring'!A15) | B105: Monitoring | C105: =IF('Monitoring'!B15="","",'Monitoring'!B15) | D105: =IF('Monitoring'!C15="","",'Monitoring'!C15) | E105: =IF('Monitoring'!D15="","",'Monitoring'!D15) | F105: =IF('Monitoring'!E15="","",'Monitoring'!E15) | G105: =IF('Monitoring'!F15="","",'Monitoring'!F15) | H105: =IF('Monitoring'!G15="","",'Monitoring'!G15) | I105: =IF('Monitoring'!H15="","",'Monitoring'!H15) | J105: =IF('Monitoring'!I15="","",'Monitoring'!I15) | ... N105: =IF('Monitoring'!M15="","",'Monitoring'!M15)
A106: =IF('DR'!A3="","",'DR'!A3) | B106: DR | C106: =IF('DR'!B3="","",'DR'!B3) | D106: =IF('DR'!C3="","",'DR'!C3) | E106: =IF('DR'!D3="","",'DR'!D3) | F106: =IF('DR'!E3="","",'DR'!E3) | G106: =IF('DR'!F3="","",'DR'!F3) | H106: =IF('DR'!G3="","",'DR'!G3) | I106: =IF('DR'!H3="","",'DR'!H3) | J106: =IF('DR'!I3="","",'DR'!I3) | ... N106: =IF('DR'!M3="","",'DR'!M3)
A107: =IF('DR'!A4="","",'DR'!A4) | B107: DR | C107: =IF('DR'!B4="","",'DR'!B4) | D107: =IF('DR'!C4="","",'DR'!C4) | E107: =IF('DR'!D4="","",'DR'!D4) | F107: =IF('DR'!E4="","",'DR'!E4) | G107: =IF('DR'!F4="","",'DR'!F4) | H107: =IF('DR'!G4="","",'DR'!G4) | I107: =IF('DR'!H4="","",'DR'!H4) | J107: =IF('DR'!I4="","",'DR'!I4) | ... N107: =IF('DR'!M4="","",'DR'!M4)
A108: =IF('DR'!A5="","",'DR'!A5) | B108: DR | C108: =IF('DR'!B5="","",'DR'!B5) | D108: =IF('DR'!C5="","",'DR'!C5) | E108: =IF('DR'!D5="","",'DR'!D5) | F108: =IF('DR'!E5="","",'DR'!E5) | G108: =IF('DR'!F5="","",'DR'!F5) | H108: =IF('DR'!G5="","",'DR'!G5) | I108: =IF('DR'!H5="","",'DR'!H5) | J108: =IF('DR'!I5="","",'DR'!I5) | ... N108: =IF('DR'!M5="","",'DR'!M5)
A109: =IF('DR'!A6="","",'DR'!A6) | B109: DR | C109: =IF('DR'!B6="","",'DR'!B6) | D109: =IF('DR'!C6="","",'DR'!C6) | E109: =IF('DR'!D6="","",'DR'!D6) | F109: =IF('DR'!E6="","",'DR'!E6) | G109: =IF('DR'!F6="","",'DR'!F6) | H109: =IF('DR'!G6="","",'DR'!G6) | I109: =IF('DR'!H6="","",'DR'!H6) | J109: =IF('DR'!I6="","",'DR'!I6) | ... N109: =IF('DR'!M6="","",'DR'!M6)
A110: =IF('DR'!A7="","",'DR'!A7) | B110: DR | C110: =IF('DR'!B7="","",'DR'!B7) | D110: =IF('DR'!C7="","",'DR'!C7) | E110: =IF('DR'!D7="","",'DR'!D7) | F110: =IF('DR'!E7="","",'DR'!E7) | G110: =IF('DR'!F7="","",'DR'!F7) | H110: =IF('DR'!G7="","",'DR'!G7) | I110: =IF('DR'!H7="","",'DR'!H7) | J110: =IF('DR'!I7="","",'DR'!I7) | ... N110: =IF('DR'!M7="","",'DR'!M7)
A111: =IF('DR'!A8="","",'DR'!A8) | B111: DR | C111: =IF('DR'!B8="","",'DR'!B8) | D111: =IF('DR'!C8="","",'DR'!C8) | E111: =IF('DR'!D8="","",'DR'!D8) | F111: =IF('DR'!E8="","",'DR'!E8) | G111: =IF('DR'!F8="","",'DR'!F8) | H111: =IF('DR'!G8="","",'DR'!G8) | I111: =IF('DR'!H8="","",'DR'!H8) | J111: =IF('DR'!I8="","",'DR'!I8) | ... N111: =IF('DR'!M8="","",'DR'!M8)
A112: =IF('DR'!A9="","",'DR'!A9) | B112: DR | C112: =IF('DR'!B9="","",'DR'!B9) | D112: =IF('DR'!C9="","",'DR'!C9) | E112: =IF('DR'!D9="","",'DR'!D9) | F112: =IF('DR'!E9="","",'DR'!E9) | G112: =IF('DR'!F9="","",'DR'!F9) | H112: =IF('DR'!G9="","",'DR'!G9) | I112: =IF('DR'!H9="","",'DR'!H9) | J112: =IF('DR'!I9="","",'DR'!I9) | ... N112: =IF('DR'!M9="","",'DR'!M9)
A113: =IF('DR'!A10="","",'DR'!A10) | B113: DR | C113: =IF('DR'!B10="","",'DR'!B10) | D113: =IF('DR'!C10="","",'DR'!C10) | E113: =IF('DR'!D10="","",'DR'!D10) | F113: =IF('DR'!E10="","",'DR'!E10) | G113: =IF('DR'!F10="","",'DR'!F10) | H113: =IF('DR'!G10="","",'DR'!G10) | I113: =IF('DR'!H10="","",'DR'!H10) | J113: =IF('DR'!I10="","",'DR'!I10) | ... N113: =IF('DR'!M10="","",'DR'!M10)
A114: =IF('DR'!A11="","",'DR'!A11) | B114: DR | C114: =IF('DR'!B11="","",'DR'!B11) | D114: =IF('DR'!C11="","",'DR'!C11) | E114: =IF('DR'!D11="","",'DR'!D11) | F114: =IF('DR'!E11="","",'DR'!E11) | G114: =IF('DR'!F11="","",'DR'!F11) | H114: =IF('DR'!G11="","",'DR'!G11) | I114: =IF('DR'!H11="","",'DR'!H11) | J114: =IF('DR'!I11="","",'DR'!I11) | ... N114: =IF('DR'!M11="","",'DR'!M11)
A115: =IF('DR'!A12="","",'DR'!A12) | B115: DR | C115: =IF('DR'!B12="","",'DR'!B12) | D115: =IF('DR'!C12="","",'DR'!C12) | E115: =IF('DR'!D12="","",'DR'!D12) | F115: =IF('DR'!E12="","",'DR'!E12) | G115: =IF('DR'!F12="","",'DR'!F12) | H115: =IF('DR'!G12="","",'DR'!G12) | I115: =IF('DR'!H12="","",'DR'!H12) | J115: =IF('DR'!I12="","",'DR'!I12) | ... N115: =IF('DR'!M12="","",'DR'!M12)
A116: =IF('DR'!A13="","",'DR'!A13) | B116: DR | C116: =IF('DR'!B13="","",'DR'!B13) | D116: =IF('DR'!C13="","",'DR'!C13) | E116: =IF('DR'!D13="","",'DR'!D13) | F116: =IF('DR'!E13="","",'DR'!E13) | G116: =IF('DR'!F13="","",'DR'!F13) | H116: =IF('DR'!G13="","",'DR'!G13) | I116: =IF('DR'!H13="","",'DR'!H13) | J116: =IF('DR'!I13="","",'DR'!I13) | ... N116: =IF('DR'!M13="","",'DR'!M13)
A117: =IF('DR'!A14="","",'DR'!A14) | B117: DR | C117: =IF('DR'!B14="","",'DR'!B14) | D117: =IF('DR'!C14="","",'DR'!C14) | E117: =IF('DR'!D14="","",'DR'!D14) | F117: =IF('DR'!E14="","",'DR'!E14) | G117: =IF('DR'!F14="","",'DR'!F14) | H117: =IF('DR'!G14="","",'DR'!G14) | I117: =IF('DR'!H14="","",'DR'!H14) | J117: =IF('DR'!I14="","",'DR'!I14) | ... N117: =IF('DR'!M14="","",'DR'!M14)
... A124: =IF('DR'!A21="","",'DR'!A21) | B124: DR | C124: =IF('DR'!B21="","",'DR'!B21) | D124: =IF('DR'!C21="","",'DR'!C21) | E124: =IF('DR'!D21="","",'DR'!D21) | F124: =IF('DR'!E21="","",'DR'!E21) | G124: =IF('DR'!F21="","",'DR'!F21) | H124: =IF('DR'!G21="","",'DR'!G21) | I124: =IF('DR'!H21="","",'DR'!H21) | J124: =IF('DR'!I21="","",'DR'!I21) | ... N124: =IF('DR'!M21="","",'DR'!M21)
A125: =IF('Best Practices'!A3="","",'Best Practices'!A3) | B125: Best Practices | C125: =IF('Best Practices'!B3="","",'Best Practices'!B3) | D125: =IF('Best Practices'!C3="","",'Best Practices'!C3) | E125: =IF('Best Practices'!D3="","",'Best Practices'!D3) | F125: =IF('Best Practices'!E3="","",'Best Practices'!E3) | G125: =IF('Best Practices'!F3="","",'Best Practices'!F3) | H125: =IF('Best Practices'!G3="","",'Best Practices'!G3) | I125: =IF('Best Practices'!H3="","",'Best Practices'!H3) | J125: =IF('Best Practices'!I3="","",'Best Practices'!I3) | ... N125: =IF('Best Practices'!M3="","",'Best Practices'!M3)
A126: =IF('Best Practices'!A4="","",'Best Practices'!A4) | B126: Best Practices | C126: =IF('Best Practices'!B4="","",'Best Practices'!B4) | D126: =IF('Best Practices'!C4="","",'Best Practices'!C4) | E126: =IF('Best Practices'!D4="","",'Best Practices'!D4) | F126: =IF('Best Practices'!E4="","",'Best Practices'!E4) | G126: =IF('Best Practices'!F4="","",'Best Practices'!F4) | H126: =IF('Best Practices'!G4="","",'Best Practices'!G4) | I126: =IF('Best Practices'!H4="","",'Best Practices'!H4) | J126: =IF('Best Practices'!I4="","",'Best Practices'!I4) | ... N126: =IF('Best Practices'!M4="","",'Best Practices'!M4)
A127: =IF('Best Practices'!A5="","",'Best Practices'!A5) | B127: Best Practices | C127: =IF('Best Practices'!B5="","",'Best Practices'!B5) | D127: =IF('Best Practices'!C5="","",'Best Practices'!C5) | E127: =IF('Best Practices'!D5="","",'Best Practices'!D5) | F127: =IF('Best Practices'!E5="","",'Best Practices'!E5) | G127: =IF('Best Practices'!F5="","",'Best Practices'!F5) | H127: =IF('Best Practices'!G5="","",'Best Practices'!G5) | I127: =IF('Best Practices'!H5="","",'Best Practices'!H5) | J127: =IF('Best Practices'!I5="","",'Best Practices'!I5) | ... N127: =IF('Best Practices'!M5="","",'Best Practices'!M5)
A128: =IF('Best Practices'!A6="","",'Best Practices'!A6) | B128: Best Practices | C128: =IF('Best Practices'!B6="","",'Best Practices'!B6) | D128: =IF('Best Practices'!C6="","",'Best Practices'!C6) | E128: =IF('Best Practices'!D6="","",'Best Practices'!D6) | F128: =IF('Best Practices'!E6="","",'Best Practices'!E6) | G128: =IF('Best Practices'!F6="","",'Best Practices'!F6) | H128: =IF('Best Practices'!G6="","",'Best Practices'!G6) | I128: =IF('Best Practices'!H6="","",'Best Practices'!H6) | J128: =IF('Best Practices'!I6="","",'Best Practices'!I6) | ... N128: =IF('Best Practices'!M6="","",'Best Practices'!M6)
A129: =IF('Best Practices'!A7="","",'Best Practices'!A7) | B129: Best Practices | C129: =IF('Best Practices'!B7="","",'Best Practices'!B7) | D129: =IF('Best Practices'!C7="","",'Best Practices'!C7) | E129: =IF('Best Practices'!D7="","",'Best Practices'!D7) | F129: =IF('Best Practices'!E7="","",'Best Practices'!E7) | G129: =IF('Best Practices'!F7="","",'Best Practices'!F7) | H129: =IF('Best Practices'!G7="","",'Best Practices'!G7) | I129: =IF('Best Practices'!H7="","",'Best Practices'!H7) | J129: =IF('Best Practices'!I7="","",'Best Practices'!I7) | ... N129: =IF('Best Practices'!M7="","",'Best Practices'!M7)
A130: =IF('Best Practices'!A8="","",'Best Practices'!A8) | B130: Best Practices | C130: =IF('Best Practices'!B8="","",'Best Practices'!B8) | D130: =IF('Best Practices'!C8="","",'Best Practices'!C8) | E130: =IF('Best Practices'!D8="","",'Best Practices'!D8) | F130: =IF('Best Practices'!E8="","",'Best Practices'!E8) | G130: =IF('Best Practices'!F8="","",'Best Practices'!F8) | H130: =IF('Best Practices'!G8="","",'Best Practices'!G8) | I130: =IF('Best Practices'!H8="","",'Best Practices'!H8) | J130: =IF('Best Practices'!I8="","",'Best Practices'!I8) | ... N130: =IF('Best Practices'!M8="","",'Best Practices'!M8)
A131: =IF('Best Practices'!A9="","",'Best Practices'!A9) | B131: Best Practices | C131: =IF('Best Practices'!B9="","",'Best Practices'!B9) | D131: =IF('Best Practices'!C9="","",'Best Practices'!C9) | E131: =IF('Best Practices'!D9="","",'Best Practices'!D9) | F131: =IF('Best Practices'!E9="","",'Best Practices'!E9) | G131: =IF('Best Practices'!F9="","",'Best Practices'!F9) | H131: =IF('Best Practices'!G9="","",'Best Practices'!G9) | I131: =IF('Best Practices'!H9="","",'Best Practices'!H9) | J131: =IF('Best Practices'!I9="","",'Best Practices'!I9) | ... N131: =IF('Best Practices'!M9="","",'Best Practices'!M9)
A132: =IF('Best Practices'!A10="","",'Best Practices'!A10) | B132: Best Practices | C132: =IF('Best Practices'!B10="","",'Best Practices'!B10) | D132: =IF('Best Practices'!C10="","",'Best Practices'!C10) | E132: =IF('Best Practices'!D10="","",'Best Practices'!D10) | F132: =IF('Best Practices'!E10="","",'Best Practices'!E10) | G132: =IF('Best Practices'!F10="","",'Best Practices'!F10) | H132: =IF('Best Practices'!G10="","",'Best Practices'!G10) | I132: =IF('Best Practices'!H10="","",'Best Practices'!H10) | J132: =IF('Best Practices'!I10="","",'Best Practices'!I10) | ... N132: =IF('Best Practices'!M10="","",'Best Practices'!M10)
A133: =IF('Best Practices'!A11="","",'Best Practices'!A11) | B133: Best Practices | C133: =IF('Best Practices'!B11="","",'Best Practices'!B11) | D133: =IF('Best Practices'!C11="","",'Best Practices'!C11) | E133: =IF('Best Practices'!D11="","",'Best Practices'!D11) | F133: =IF('Best Practices'!E11="","",'Best Practices'!E11) | G133: =IF('Best Practices'!F11="","",'Best Practices'!F11) | H133: =IF('Best Practices'!G11="","",'Best Practices'!G11) | I133: =IF('Best Practices'!H11="","",'Best Practices'!H11) | J133: =IF('Best Practices'!I11="","",'Best Practices'!I11) | ... N133: =IF('Best Practices'!M11="","",'Best Practices'!M11)
A134: =IF('Best Practices'!A12="","",'Best Practices'!A12) | B134: Best Practices | C134: =IF('Best Practices'!B12="","",'Best Practices'!B12) | D134: =IF('Best Practices'!C12="","",'Best Practices'!C12) | E134: =IF('Best Practices'!D12="","",'Best Practices'!D12) | F134: =IF('Best Practices'!E12="","",'Best Practices'!E12) | G134: =IF('Best Practices'!F12="","",'Best Practices'!F12) | H134: =IF('Best Practices'!G12="","",'Best Practices'!G12) | I134: =IF('Best Practices'!H12="","",'Best Practices'!H12) | J134: =IF('Best Practices'!I12="","",'Best Practices'!I12) | ... N134: =IF('Best Practices'!M12="","",'Best Practices'!M12)
A135: =IF('Best Practices'!A13="","",'Best Practices'!A13) | B135: Best Practices | C135: =IF('Best Practices'!B13="","",'Best Practices'!B13) | D135: =IF('Best Practices'!C13="","",'Best Practices'!C13) | E135: =IF('Best Practices'!D13="","",'Best Practices'!D13) | F135: =IF('Best Practices'!E13="","",'Best Practices'!E13) | G135: =IF('Best Practices'!F13="","",'Best Practices'!F13) | H135: =IF('Best Practices'!G13="","",'Best Practices'!G13) | I135: =IF('Best Practices'!H13="","",'Best Practices'!H13) | J135: =IF('Best Practices'!I13="","",'Best Practices'!I13) | ... N135: =IF('Best Practices'!M13="","",'Best Practices'!M13)
A136: =IF('Best Practices'!A14="","",'Best Practices'!A14) | B136: Best Practices | C136: =IF('Best Practices'!B14="","",'Best Practices'!B14) | D136: =IF('Best Practices'!C14="","",'Best Practices'!C14) | E136: =IF('Best Practices'!D14="","",'Best Practices'!D14) | F136: =IF('Best Practices'!E14="","",'Best Practices'!E14) | G136: =IF('Best Practices'!F14="","",'Best Practices'!F14) | H136: =IF('Best Practices'!G14="","",'Best Practices'!G14) | I136: =IF('Best Practices'!H14="","",'Best Practices'!H14) | J136: =IF('Best Practices'!I14="","",'Best Practices'!I14) | ... N136: =IF('Best Practices'!M14="","",'Best Practices'!M14)
...

Sheet Project
A1: Project Parameters
A2: Parameter Name | B2: Production | C2: Test | D2: DR | E2: Description | F2: Required | G2: Data Type | H2: Validation Rules | I2: Security Level | J2: Owner Team | K2: Dependencies | L2: Notes | M2: Last Updated
A3: solution.name | B3: intelligent-document-processing | C3: intelligent-document-processing | D3: intelligent-document-processing | E3: Solution name for resource naming | F3: Yes | G3: String | H3: Valid string value | I3: Public | J3: Development | L3: IDP solution identifier | M3: 2025-12-01
A4: solution.abbr | B4: idp | C4: idp | D4: idp | E4: Solution abbreviation (3-4 chars) | F4: Yes | G4: String | H4: Valid string value | I4: Public | J4: Development | L4: Used in resource naming prefix | M4: 2025-12-01
A5: solution.provider_name | B5: aws | C5: aws | D5: aws | E5: Provider organization name | F5: Yes | G5: String | H5: Valid string value | I5: Public | J5: Development | L5: AWS provider | M5: 2025-12-01
A6: solution.category_name | B6: ai | C6: ai | D6: ai | E6: Solution category | F6: Yes | G6: String | H6: Valid string value | I6: Public | J6: Development | L6: AI category | M6: 2025-12-01
A7: aws.region | B7: us-east-1 | C7: us-east-1 | D7: us-west-2 | E7: Primary AWS region | F7: Yes | G7: String | H7: Valid region | I7: Public | J7: Infrastructure | L7: From SOW AWS_REGION | M7: 2025-12-01
A8: aws.dr_region | B8: us-west-2 | C8: us-west-2 | D8: us-east-1 | E8: DR region | F8: Yes | G8: String | H8: Valid region | I8: Public | J8: Infrastructure | L8: From SOW AWS_DR_REGION | M8: 2025-12-01
A9: aws.profile | E9: AWS CLI profile (optional) | F9: No | G9: String | H9: Valid profile | I9: Confidential | J9: Infrastructure | L9: Leave empty for default | M9: 2025-12-01
A10: ownership.cost_center | B10: CC-IDP-001 | C10: CC-IDP-001 | D10: CC-IDP-001 | E10: Cost center | F10: Yes | G10: String | H10: Valid string | I10: Public | J10: Infrastructure | L10: From SOW COST_ALLOCATION_TAGS | M10: 2025-12-01
A11: ownership.owner_email | B11: idp-team@example.com | C11: idp-team@example.com | D11: idp-team@example.com | E11: Owner email | F11: Yes | G11: String | H11: Valid email | I11: Confidential | J11: Infrastructure | L11: Team notifications | M11: 2025-12-01
A12: ownership.project_code | B12: PRJ-IDP-2025 | C12: PRJ-IDP-2025 | D12: PRJ-IDP-2025 | E12: Project code | F12: Yes | G12: String | H12: Valid string | I12: Public | J12: Infrastructure | L12: Tracking code | M12: 2025-12-01

Sheet Security
A1: Security Parameters
A2: Parameter Name | B2: Production | C2: Test | D2: DR | E2: Description | F2: Required | G2: Data Type | H2: Validation Rules | I2: Security Level | J2: Owner Team | K2: Dependencies | L2: Notes | M2: Last Updated
A3: security.kms_deletion_window_days | B3: 30 | C3: 7 | D3: 30 | E3: KMS key deletion window (days) | F3: Yes | G3: Integer | H3: 7-30 | I3: Public | J3: Security | L3: Protection period | M3: 2025-12-01
A4: security.enable_kms_key_rotation | B4: true | C4: true | D4: true | E4: Enable KMS key rotation | F4: Yes | G4: Boolean | H4: true|false | I4: Public | J4: Security | L4: Security best practice | M4: 2025-12-01
A5: auth.enabled | B5: true | C5: true | D5: true | E5: Enable Cognito authentication | F5: Yes | G5: Boolean | H5: true|false | I5: Public | J5: Security | L5: API auth | M5: 2025-12-01
A6: auth.username_attributes | B6: ["email"] | C6: ["email"] | D6: ["email"] | E6: Username attributes | F6: Yes | G6: List(String) | H6: Valid attributes | I6: Public | J6: Security | L6: Email login | M6: 2025-12-01
A7: auth.auto_verified_attributes | B7: ["email"] | C7: ["email"] | D7: ["email"] | E7: Auto-verified attributes | F7: Yes | G7: List(String) | H7: Valid attributes | I7: Public | J7: Security | L7: Email verification | M7: 2025-12-01
A8: auth.password_minimum_length | B8: 12 | C8: 8 | D8: 12 | E8: Minimum password length | F8: Yes | G8: Integer | H8: 8-99 | I8: Public | J8: Security | L8: Password policy | M8: 2025-12-01
A9: auth.password_require_lowercase | B9: true | C9: true | D9: true | E9: Require lowercase | F9: Yes | G9: Boolean | H9: true|false | I9: Public | J9: Security | L9: Password policy | M9: 2025-12-01
A10: auth.password_require_numbers | B10: true | C10: true | D10: true | E10: Require numbers | F10: Yes | G10: Boolean | H10: true|false | I10: Public | J10: Security | L10: Password policy | M10: 2025-12-01
A11: auth.password_require_symbols | B11: true | C11: false | D11: true | E11: Require symbols | F11: Yes | G11: Boolean | H11: true|false | I11: Public | J11: Security | L11: Password policy | M11: 2025-12-01
A12: auth.password_require_uppercase | B12: true | C12: true | D12: true | E12: Require uppercase | F12: Yes | G12: Boolean | H12: true|false | I12: Public | J12: Security | L12: Password policy | M12: 2025-12-01
A13: auth.mfa_configuration | B13: OPTIONAL | C13: OFF | D13: OPTIONAL | E13: MFA configuration | F13: Yes | G13: String | H13: OFF|OPTIONAL|ON | I13: Public | J13: Security | L13: Multi-factor auth | M13: 2025-12-01
A14: auth.advanced_security_mode | B14: AUDIT | C14: OFF | D14: AUDIT | E14: Advanced security mode | F14: Yes | G14: String | H14: OFF|AUDIT|ENFORCED | I14: Public | J14: Security | L14: Threat detection | M14: 2025-12-01
A15: auth.domain | E15: Cognito domain prefix | F15: No | G15: String | H15: Valid domain | I15: Public | J15: Security | L15: Custom domain | M15: 2025-12-01
A16: auth.callback_urls | B16: [] | C16: [] | D16: [] | E16: OAuth callback URLs | F16: No | G16: List(String) | H16: Valid URLs | I16: Public | J16: Security | L16: OAuth config | M16: 2025-12-01
A17: auth.logout_urls | B17: [] | C17: [] | D17: [] | E17: OAuth logout URLs | F17: No | G17: List(String) | H17: Valid URLs | I17: Public | J17: Security | L17: OAuth config | M17: 2025-12-01

Sheet Storage
A1: Storage Parameters
A2: Parameter Name | B2: Production | C2: Test | D2: DR | E2: Description | F2: Required | G2: Data Type | H2: Validation Rules | I2: Security Level | J2: Owner Team | K2: Dependencies | L2: Notes | M2: Last Updated
A3: storage.force_destroy | B3: false | C3: true | D3: false | E3: Allow S3 bucket destruction | F3: Yes | G3: Boolean | H3: true|false | I3: Public | J3: Infrastructure | L3: Test only | M3: 2025-12-01
A4: storage.versioning_enabled | B4: true | C4: true | D4: true | E4: Enable S3 versioning | F4: Yes | G4: Boolean | H4: true|false | I4: Public | J4: Infrastructure | L4: DR requirement | M4: 2025-12-01
A5: storage.transition_to_ia_days | B5: 30 | C5: 30 | D5: 30 | E5: Transition to S3-IA (days) | F5: Yes | G5: Integer | H5: Positive integer | I5: Public | J5: Infrastructure | L5: Cost optimization | M5: 2025-12-01
A6: storage.transition_to_glacier_days | B6: 90 | C6: 60 | D6: 90 | E6: Transition to Glacier (days) | F6: Yes | G6: Integer | H6: Positive integer | I6: Public | J6: Infrastructure | L6: Long-term storage | M6: 2025-12-01
A7: storage.document_expiration_days | B7: 365 | C7: 90 | D7: 365 | E7: Document expiration (days) | F7: Yes | G7: Integer | H7: Positive integer | I7: Public | J7: Infrastructure | L7: Data retention | M7: 2025-12-01
A8: storage.noncurrent_version_expiration_days | B8: 30 | C8: 7 | D8: 30 | E8: Noncurrent version expiration | F8: Yes | G8: Integer | H8: Positive integer | I8: Public | J8: Infrastructure | L8: Version cleanup | M8: 2025-12-01
A9: storage.enable_direct_upload | B9: true | C9: true | D9: true | E9: Enable direct S3 upload | F9: Yes | G9: Boolean | H9: true|false | I9: Public | J9: Infrastructure | L9: Presigned URLs | M9: 2025-12-01
A10: storage.cors_allowed_origins | B10: ["*"] | C10: ["*"] | D10: ["*"] | E10: CORS allowed origins | F10: Yes | G10: List(String) | H10: Valid origins | I10: Public | J10: Infrastructure | L10: API access | M10: 2025-12-01
A11: storage.create_output_bucket | B11: true | C11: true | D11: true | E11: Create output bucket | F11: Yes | G11: Boolean | H11: true|false | I11: Public | J11: Infrastructure | L11: Processed results | M11: 2025-12-01
A12: storage.output_expiration_days | B12: 30 | C12: 7 | D12: 30 | E12: Output expiration (days) | F12: Yes | G12: Integer | H12: Positive integer | I12: Public | J12: Infrastructure | L12: Results retention | M12: 2025-12-01

Sheet Database
A1: Database Parameters
A2: Parameter Name | B2: Production | C2: Test | D2: DR | E2: Description | F2: Required | G2: Data Type | H2: Validation Rules | I2: Security Level | J2: Owner Team | K2: Dependencies | L2: Notes | M2: Last Updated
A3: database.billing_mode | B3: PAY_PER_REQUEST | C3: PAY_PER_REQUEST | D3: PAY_PER_REQUEST | E3: DynamoDB billing mode | F3: Yes | G3: String | H3: PAY_PER_REQUEST|PROVISIONED | I3: Public | J3: Infrastructure | L3: On-demand for variable load | M3: 2025-12-01
A4: database.read_capacity | B4: 5 | C4: 5 | D4: 5 | E4: DynamoDB read capacity (PROVISIONED) | F4: Yes | G4: Integer | H4: Positive integer | I4: Public | J4: Infrastructure | L4: Only for PROVISIONED | M4: 2025-12-01
A5: database.write_capacity | B5: 5 | C5: 5 | D5: 5 | E5: DynamoDB write capacity (PROVISIONED) | F5: Yes | G5: Integer | H5: Positive integer | I5: Public | J5: Infrastructure | L5: Only for PROVISIONED | M5: 2025-12-01
A6: database.gsi_read_capacity | B6: 5 | C6: 5 | D6: 5 | E6: GSI read capacity (PROVISIONED) | F6: Yes | G6: Integer | H6: Positive integer | I6: Public | J6: Infrastructure | L6: Only for PROVISIONED | M6: 2025-12-01
A7: database.gsi_write_capacity | B7: 5 | C7: 5 | D7: 5 | E7: GSI write capacity (PROVISIONED) | F7: Yes | G7: Integer | H7: Positive integer | I7: Public | J7: Infrastructure | L7: Only for PROVISIONED | M7: 2025-12-01
A8: database.ttl_enabled | B8: true | C8: true | D8: true | E8: Enable TTL | F8: Yes | G8: Boolean | H8: true|false | I8: Public | J8: Infrastructure | L8: Auto-expire old records | M8: 2025-12-01
A9: database.point_in_time_recovery | B9: true | C9: false | D9: true | E9: Enable point-in-time recovery | F9: Yes | G9: Boolean | H9: true|false | I9: Public | J9: Infrastructure | L9: PITR backup | M9: 2025-12-01
A10: database.stream_enabled | B10: false | C10: false | D10: false | E10: Enable DynamoDB streams | F10: Yes | G10: Boolean | H10: true|false | I10: Public | J10: Infrastructure | L10: Event processing | M10: 2025-12-01
A11: database.stream_view_type | B11: NEW_AND_OLD_IMAGES | C11: NEW_AND_OLD_IMAGES | D11: NEW_AND_OLD_IMAGES | E11: Stream view type | F11: Yes | G11: String | H11: Valid stream type | I11: Public | J11: Infrastructure | L11: If streams enabled | M11: 2025-12-01
A12: database.enable_autoscaling | B12: false | C12: false | D12: false | E12: Enable autoscaling | F12: Yes | G12: Boolean | H12: true|false | I12: Public | J12: Infrastructure | L12: Only for PROVISIONED | M12: 2025-12-01
A13: database.autoscaling_min_read | B13: 5 | C13: 5 | D13: 5 | E13: Autoscaling min read | F13: Yes | G13: Integer | H13: Positive integer | I13: Public | J13: Infrastructure | L13: Only for PROVISIONED | M13: 2025-12-01
A14: database.autoscaling_max_read | B14: 100 | C14: 50 | D14: 100 | E14: Autoscaling max read | F14: Yes | G14: Integer | H14: Positive integer | I14: Public | J14: Infrastructure | L14: Only for PROVISIONED | M14: 2025-12-01
... A17: database.autoscaling_target_utilization | B17: 70 | C17: 70 | D17: 70 | E17: Autoscaling target utilization | F17: Yes | G17: Integer | H17: 0-100 | I17: Public | J17: Infrastructure | L17: Target percentage | M17: 2025-12-01

Sheet Application
A1: Application Parameters
A2: Parameter Name | B2: Production | C2: Test | D2: DR | E2: Description | F2: Required | G2: Data Type | H2: Validation Rules | I2: Security Level | J2: Owner Team | K2: Dependencies | L2: Notes | M2: Last Updated
A3: application.lambda_runtime | B3: python3.11 | C3: python3.11 | D3: python3.11 | E3: Lambda runtime | F3: Yes | G3: String | H3: Valid runtime | I3: Public | J3: Development | L3: Python 3.11 | M3: 2025-12-01
A4: application.lambda_vpc_enabled | B4: false | C4: false | D4: false | E4: Enable Lambda VPC mode | F4: Yes | G4: Boolean | H4: true|false | I4: Public | J4: Development | L4: Requires network.vpc_id and network.private_subnet_ids | M4: 2025-12-01
A5: textract.supported_document_types | B5: ["pdf", "png", "jpg", "jpeg", "tiff"] | C5: ["pdf", "png", "jpg", "jpeg", "tiff"] | D5: ["pdf", "png", "jpg", "jpeg", "tiff"] | E5: Supported document types | F5: Yes | G5: List(String) | H5: Valid types | I5: Public | J5: AI/ML Team | L5: Textract supported formats | M5: 2025-12-01
A6: textract.max_file_size_mb | B6: 50 | C6: 50 | D6: 50 | E6: Maximum file size (MB) | F6: Yes | G6: Integer | H6: 1-100 | I6: Public | J6: AI/ML Team | L6: Textract limit | M6: 2025-12-01
A7: textract.confidence_threshold | B7: 80 | C7: 80 | D7: 80 | E7: Minimum confidence for auto-processing | F7: Yes | G7: Integer | H7: 0-100 | I7: Public | J7: AI/ML Team | L7: Below routes to human review | M7: 2025-12-01
A8: textract.polling_interval_seconds | B8: 30 | C8: 30 | D8: 30 | E8: Async polling interval | F8: Yes | G8: Integer | H8: 1-300 | I8: Public | J8: AI/ML Team | L8: Check job status | M8: 2025-12-01
A9: textract.max_polling_attempts | B9: 20 | C9: 20 | D9: 20 | E9: Max polling attempts | F9: Yes | G9: Integer | H9: 1-100 | I9: Public | J9: AI/ML Team | L9: Timeout protection | M9: 2025-12-01
A10: textract.enable_tables | B10: true | C10: true | D10: true | E10: Enable table extraction | F10: Yes | G10: Boolean | H10: true|false | I10: Public | J10: AI/ML Team | L10: Extract tables | M10: 2025-12-01
A11: textract.enable_forms | B11: true | C11: true | D11: true | E11: Enable form extraction | F11: Yes | G11: Boolean | H11: true|false | I11: Public | J11: AI/ML Team | L11: Extract forms | M11: 2025-12-01
A12: textract.enable_queries | B12: false | C12: false | D12: false | E12: Enable queries feature | F12: Yes | G12: Boolean | H12: true|false | I12: Public | J12: AI/ML Team | L12: Custom queries | M12: 2025-12-01
A13: textract.enable_signatures | B13: false | C13: false | D13: false | E13: Enable signature detection | F13: Yes | G13: Boolean | H13: true|false | I13: Public | J13: AI/ML Team | L13: Signature detection | M13: 2025-12-01
A14: textract.enable_expense | B14: false | C14: false | D14: false | E14: Enable expense analysis | F14: Yes | G14: Boolean | H14: true|false | I14: Public | J14: AI/ML Team | L14: Receipt/invoice | M14: 2025-12-01
... A23: human_review.use_private_workforce | B23: true | C23: true | D23: true | E23: Use private workforce | F23: Yes | G23: Boolean | H23: true|false | I23: Public | J23: AI/ML Team | L23: Internal reviewers | M23: 2025-12-01
A24: human_review.workteam_arn | E24: SageMaker workteam ARN | F24: No | G24: String | H24: Valid ARN | I24: Confidential | J24: AI/ML Team | L24: Private team ARN | M24: 2025-12-01
A25: human_review.task_price_usd | B25: 0.05 | C25: 0.05 | D25: 0.05 | E25: Task price (USD) | F25: Yes | G25: String | H25: Valid number | I25: Public | J25: AI/ML Team | L25: Per task cost | M25: 2025-12-01
A26: human_review.task_title | B26: Document Review Task | C26: Document Review Task | D26: Document Review Task | E26: Task title | F26: Yes | G26: String | H26: Valid string | I26: Public | J26: AI/ML Team | L26: Shown to workers | M26: 2025-12-01
A27: human_review.task_description | B27: Review the extracted document data and verify accuracy | C27: Review the extracted document data and verify accuracy | D27: Review the extracted document data and verify accuracy | E27: Task description | F27: Yes | G27: String | H27: Valid string | I27: Public | J27: AI/ML Team | L27: Worker instructions | M27: 2025-12-01
A28: human_review.task_count | B28: 1 | C28: 1 | D28: 1 | E28: Workers per task | F28: Yes | G28: Integer | H28: 1-10 | I28: Public | J28: AI/ML Team | L28: Redundancy | M28: 2025-12-01
A29: human_review.task_availability_seconds | B29: 43200 | C29: 43200 | D29: 43200 | E29: Task availability (seconds) | F29: Yes | G29: Integer | H29: Positive integer | I29: Public | J29: AI/ML Team | L29: 12 hours | M29: 2025-12-01
A30: human_review.confidence_threshold | B30: 80 | C30: 80 | D30: 80 | E30: Confidence threshold | F30: Yes | G30: Integer | H30: 0-100 | I30: Public | J30: AI/ML Team | L30: Route to review | M30: 2025-12-01
A31: human_review.custom_ui_template | E31: Custom UI template | F31: No | G31: String | H31: Valid path | I31: Public | J31: AI/ML Team | L31: Optional custom UI | M31: 2025-12-01
A32: api.version | B32: 1.0.0 | C32: 1.0.0 | D32: 1.0.0 | E32: API version | F32: Yes | G32: String | H32: Semantic versioning | I32: Public | J32: Development | L32: API versioning | M32: 2025-12-01
A33: api.stage_name | B33: v1 | C33: v1 | D33: v1 | E33: API Gateway stage | F33: Yes | G33: String | H33: Valid stage | I33: Public | J33: Development | L33: Deployment stage | M33: 2025-12-01
A34: api.endpoint_type | B34: REGIONAL | C34: REGIONAL | D34: REGIONAL | E34: API endpoint type | F34: Yes | G34: String | H34: REGIONAL|EDGE|PRIVATE | I34: Public | J34: Development | L34: Regional API | M34: 2025-12-01
A35: api.enable_cors | B35: true | C35: true | D35: true | E35: Enable CORS | F35: Yes | G35: Boolean | H35: true|false | I35: Public | J35: Development | L35: Cross-origin access | M35: 2025-12-01
A36: api.max_file_size_mb | B36: 50 | C36: 50 | D36: 50 | E36: Max upload size (MB) | F36: Yes | G36: Integer | H36: 1-100 | I36: Public | J36: Development | L36: Request limit | M36: 2025-12-01
A37: api.default_page_size | B37: 20 | C37: 20 | D37: 20 | E37: Default pagination size | F37: Yes | G37: Integer | H37: 1-100 | I37: Public | J37: Development | L37: List results | M37: 2025-12-01
A38: api.throttling_burst_limit | B38: 1000 | C38: 100 | D38: 1000 | E38: API burst limit | F38: Yes | G38: Integer | H38: 0-10000 | I38: Public | J38: Development | L38: From SOW | M38: 2025-12-01
A39: api.throttling_rate_limit | B39: 500 | C39: 50 | D39: 500 | E39: API steady-state rate | F39: Yes | G39: Integer | H39: 0-10000 | I39: Public | J39: Development | L39: From SOW | M39: 2025-12-01
A40: api.allowed_content_types | B40: ["application/pdf", "image/png", "image/jpeg", "image/tiff"] | C40: ["application/pdf", "image/png", "image/jpeg", "image/tiff"] | D40: ["application/pdf", "image/png", "image/jpeg", "image/tiff"] | E40: Allowed content types | F40: Yes | G40: List(String) | H40: Valid types | I40: Public | J40: Development | L40: Upload validation | M40: 2025-12-01

Sheet Monitoring
A1: Monitoring Parameters
A2: Parameter Name | B2: Production | C2: Test | D2: DR | E2: Description | F2: Required | G2: Data Type | H2: Validation Rules | I2: Security Level | J2: Owner Team | K2: Dependencies | L2: Notes | M2: Last Updated
A3: logging.retention_days | B3: 30 | C3: 7 | D3: 30 | E3: CloudWatch log retention | F3: Yes | G3: Integer | H3: Positive integer | I3: Public | J3: Operations | L3: Log retention | M3: 2025-12-01
A4: logging.step_functions_log_level | B4: ERROR | C4: ALL | D4: ERROR | E4: Step Functions log level | F4: Yes | G4: String | H4: ALL|ERROR|FATAL|OFF | I4: Public | J4: Operations | L4: SFN logging | M4: 2025-12-01
A5: logging.api_gateway_log_level | B5: INFO | C5: INFO | D5: INFO | E5: API Gateway log level | F5: Yes | G5: String | H5: OFF|ERROR|INFO | I5: Public | J5: Operations | L5: API logging | M5: 2025-12-01
A6: logging.data_trace_enabled | B6: false | C6: true | D6: false | E6: Enable data tracing | F6: Yes | G6: Boolean | H6: true|false | I6: Public | J6: Operations | L6: Request/response logs | M6: 2025-12-01
A7: monitoring.xray_enabled | B7: true | C7: true | D7: true | E7: Enable X-Ray tracing | F7: Yes | G7: Boolean | H7: true|false | I7: Public | J7: Operations | L7: Distributed tracing | M7: 2025-12-01
A8: monitoring.enable_alarms | B8: true | C8: false | D8: true | E8: Enable CloudWatch alarms | F8: Yes | G8: Boolean | H8: true|false | I8: Public | J8: Operations | L8: Alert notifications | M8: 2025-12-01
A9: monitoring.sns_topic_arn | E9: SNS topic for alerts | F9: No | G9: String | H9: Valid ARN | I9: Confidential | J9: Operations | L9: Alert destination | M9: 2025-12-01
A10: monitoring.api_error_threshold | B10: 10 | C10: 50 | D10: 10 | E10: API 5xx error threshold | F10: Yes | G10: Integer | H10: Positive integer | I10: Public | J10: Operations | L10: Alert trigger | M10: 2025-12-01
A11: monitoring.api_4xx_threshold | B11: 100 | C11: 200 | D11: 100 | E11: API 4xx error threshold | F11: Yes | G11: Integer | H11: Positive integer | I11: Public | J11: Operations | L11: Client error alert | M11: 2025-12-01
A12: monitoring.api_latency_p95_ms | B12: 2000 | C12: 5000 | D12: 2000 | E12: API p95 latency threshold (ms) | F12: Yes | G12: Integer | H12: Positive integer | I12: Public | J12: Operations | L12: <2 sec target | M12: 2025-12-01
A13: monitoring.sfn_failure_threshold | B13: 5 | C13: 20 | D13: 5 | E13: Step Functions failure threshold | F13: Yes | G13: Integer | H13: Positive integer | I13: Public | J13: Operations | L13: Alert trigger | M13: 2025-12-01
A14: monitoring.lambda_error_rate_percent | B14: 5 | C14: 10 | D14: 5 | E14: Lambda error rate threshold (%) | F14: Yes | G14: Integer | H14: 0-100 | I14: Public | J14: Operations | L14: Alert on errors | M14: 2025-12-01
A15: monitoring.lambda_duration_p95_ms | B15: 60000 | C15: 60000 | D15: 60000 | E15: Lambda p95 duration threshold (ms) | F15: Yes | G15: Integer | H15: Positive integer | I15: Public | J15: Operations | L15: Performance alert | M15: 2025-12-01

Sheet DR
A1: DR Parameters
A2: Parameter Name | B2: Production | C2: Test | D2: DR | E2: Description | F2: Required | G2: Data Type | H2: Validation Rules | I2: Security Level | J2: Owner Team | K2: Dependencies | L2: Notes | M2: Last Updated
A3: dr.enabled | B3: true | C3: false | D3: true | E3: Enable DR infrastructure | F3: Yes | G3: Boolean | H3: true|false | I3: Public | J3: Operations | L3: Master DR toggle | M3: 2025-12-01
A4: dr.strategy | B4: ACTIVE_PASSIVE | C4: BACKUP_ONLY | D4: ACTIVE_PASSIVE | E4: DR strategy | F4: Yes | G4: String | H4: ACTIVE_PASSIVE|ACTIVE_ACTIVE|BACKUP_ONLY | I4: Public | J4: Operations | L4: Recovery approach | M4: 2025-12-01
A5: dr.rto_minutes | B5: 240 | C5: 480 | D5: 240 | E5: Recovery Time Objective (minutes) | F5: Yes | G5: Integer | H5: Positive integer | I5: Public | J5: Operations | L5: Target recovery time | M5: 2025-12-01
A6: dr.rpo_minutes | B6: 60 | C6: 1440 | D6: 60 | E6: Recovery Point Objective (minutes) | F6: Yes | G6: Integer | H6: Positive integer | I6: Public | J6: Operations | L6: Max data loss window | M6: 2025-12-01
A7: dr.failover_mode | B7: manual | C7: manual | D7: manual | E7: Failover mode | F7: Yes | G7: String | H7: manual|automatic | I7: Public | J7: Operations | L7: Manual for safety | M7: 2025-12-01
A8: dr.replication_enabled | B8: true | C8: false | D8: false | E8: Enable cross-region replication | F8: Yes | G8: Boolean | H8: true|false | I8: Public | J8: Operations | L8: S3 CRR and DynamoDB | M8: 2025-12-01
A9: dr.storage_replication_class | B9: STANDARD | C9: STANDARD | D9: STANDARD | E9: DR storage class | F9: Yes | G9: String | H9: Valid class | I9: Public | J9: Operations | L9: S3 storage class | M9: 2025-12-01
A10: dr.enable_replication_time_control | B10: true | C10: true | D10: true | E10: Enable replication time control | F10: Yes | G10: Boolean | H10: true|false | I10: Public | J10: Operations | L10: Predictable replication | M10: 2025-12-01
A11: dr.vault_enabled | B11: true | C11: false | D11: true | E11: Enable DR backup vault | F11: Yes | G11: Boolean | H11: true|false | I11: Public | J11: Operations | L11: DR vault in DR region | M11: 2025-12-01
A12: dr.vault_kms_deletion_window_days | B12: 30 | C12: 30 | D12: 30 | E12: DR KMS deletion window | F12: Yes | G12: Integer | H12: 7-30 | I12: Public | J12: Operations | L12: Protection period | M12: 2025-12-01
A13: dr.vault_transition_to_ia_days | B13: 30 | C13: 30 | D13: 30 | E13: DR vault transition to IA | F13: Yes | G13: Integer | H13: Positive integer | I13: Public | J13: Operations | L13: Cost optimization | M13: 2025-12-01
A14: dr.vault_noncurrent_version_expiration_days | B14: 90 | C14: 90 | D14: 90 | E14: DR vault noncurrent expiration | F14: Yes | G14: Integer | H14: Positive integer | I14: Public | J14: Operations | L14: Version cleanup | M14: 2025-12-01
... A19: dr.weekly_backup_retention_days | B19: 90 | C19: 90 | D19: 90 | E19: DR weekly retention | F19: Yes | G19: Integer | H19: Positive integer | I19: Public | J19: Operations | L19: 3 months | M19: 2025-12-01
A20: dr.test_schedule | B20: cron(0 2 ? * SUN *) | D20: cron(0 2 ? * SUN *) | E20: DR test schedule | F20: No | G20: String | H20: Valid cron | I20: Public | J20: Operations | L20: Weekly DR test | M20: 2025-12-01
A21: dr.notification_email | B21: dr-alerts@example.com | C21: dr-alerts@example.com | D21: dr-alerts@example.com | E21: DR notification email | F21: No | G21: String | H21: Valid email | I21: Confidential | J21: Operations | L21: Alert notifications | M21: 2025-12-01

Sheet Best Practices
A1: Best Practices Parameters
A2: Parameter Name | B2: Production | C2: Test | D2: DR | E2: Description | F2: Required | G2: Data Type | H2: Validation Rules | I2: Security Level | J2: Owner Team | K2: Dependencies | L2: Notes | M2: Last Updated
A3: budget.enabled | B3: true | C3: false | D3: true | E3: [Cost Optimization] Enable AWS Budgets tracking | F3: Yes | G3: Boolean | H3: true|false | I3: Public | J3: Operations | L3: Proactive cost monitoring for AI services | M3: 2025-12-01
A4: budget.monthly_amount | B4: 1500 | C4: 500 | D4: 1500 | E4: [Cost Optimization] Monthly budget limit (USD) | F4: Yes | G4: Integer | H4: Valid integer | I4: Public | J4: Operations | L4: Based on SOW cost estimates | M4: 2025-12-01
A5: budget.alert_thresholds | B5: [50, 80, 100] | C5: [80, 100] | D5: [50, 80, 100] | E5: [Cost Optimization] Budget alert thresholds (%) | F5: Yes | G5: List(Number) | H5: 0-100 | I5: Public | J5: Operations | L5: Multi-tier alerts | M5: 2025-12-01
A6: budget.enable_forecast_alert | B6: true | C6: false | D6: true | E6: [Cost Optimization] Enable forecasted spend alerts | F6: Yes | G6: Boolean | H6: true|false | I6: Public | J6: Operations | L6: ML-based spend forecasting | M6: 2025-12-01
A7: budget.alert_emails | B7: [] | C7: [] | D7: [] | E7: [Cost Optimization] Alert email addresses | F7: No | G7: List(String) | H7: Valid emails | I7: Confidential | J7: Operations | L7: Additional email recipients | M7: 2025-12-01
A8: config_rules.enabled | B8: true | C8: false | D8: true | E8: [Operational Excellence] Enable AWS Config rules | F8: Yes | G8: Boolean | H8: true|false | I8: Public | J8: Operations | L8: Compliance monitoring and drift detection | M8: 2025-12-01
A9: config_rules.enable_recorder | B9: true | C9: true | D9: true | E9: [Operational Excellence] Enable Config recorder | F9: Yes | G9: Boolean | H9: true|false | I9: Public | J9: Operations | L9: Records configuration changes | M9: 2025-12-01
A10: config_rules.retention_days | B10: 365 | C10: 90 | D10: 365 | E10: [Operational Excellence] Config history retention (days) | F10: Yes | G10: Integer | H10: Positive integer | I10: Public | J10: Operations | L10: One-year retention for audits | M10: 2025-12-01
A11: config_rules.enable_security_rules | B11: true | C11: true | D11: true | E11: [Operational Excellence] Enable security compliance rules | F11: Yes | G11: Boolean | H11: true|false | I11: Public | J11: Operations | L11: S3 encryption KMS rotation checks | M11: 2025-12-01
A12: config_rules.enable_reliability_rules | B12: true | C12: false | D12: true | E12: [Operational Excellence] Enable reliability compliance rules | F12: Yes | G12: Boolean | H12: true|false | I12: Public | J12: Operations | L12: Backup and versioning checks | M12: 2025-12-01
A13: guardduty.enabled | B13: true | C13: false | D13: true | E13: [Security] Enable GuardDuty threat detection | F13: Yes | G13: Boolean | H13: true|false | I13: Public | J13: Operations | L13: ML-based threat detection | M13: 2025-12-01
A14: guardduty.enable_s3_protection | B14: true | C14: true | D14: true | E14: [Security] Enable S3 data event monitoring | F14: Yes | G14: Boolean | H14: true|false | I14: Public | J14: Operations | L14: Detects suspicious S3 access | M14: 2025-12-01
... A16: guardduty.severity_threshold | B16: 7 | C16: 7 | D16: 7 | E16: [Security] Minimum alert severity threshold (1-10) | F16: Yes | G16: Integer | H16: 1-10 | I16: Public | J16: Operations | L16: 7+ filters to high/critical findings | M16: 2025-12-01
